cellmap_flow/__init__.py
cellmap_flow/globals.py
cellmap_flow/image_data_interface.py
cellmap_flow/inferencer.py
cellmap_flow/server.py
cellmap_flow/blockwise/__init__.py
cellmap_flow/blockwise/blockwise_processor.py
cellmap_flow/blockwise/cli.py
cellmap_flow/cli/__init__.py
cellmap_flow/cli/cli.py
cellmap_flow/cli/multiple_cli.py
cellmap_flow/cli/multiple_yaml_cli.py
cellmap_flow/cli/server_cli.py
cellmap_flow/dashboard/__init__.py
cellmap_flow/dashboard/app.py
cellmap_flow/dashboard/static/css/dark.css
cellmap_flow/dashboard/static/img/favicon.ico
cellmap_flow/dashboard/static/js/dashboard_script.js
cellmap_flow/dashboard/templates/_code_box.html
cellmap_flow/dashboard/templates/_dashboard.html
cellmap_flow/dashboard/templates/_input_tab.html
cellmap_flow/dashboard/templates/_models_tab.html
cellmap_flow/dashboard/templates/_output_tab.html
cellmap_flow/dashboard/templates/index.html
cellmap_flow/models/__init__.py
cellmap_flow/models/cellmap_models.py
cellmap_flow/models/model_yaml.py
cellmap_flow/models/run.py
cellmap_flow/norm/__init__.py
cellmap_flow/norm/input_normalize.py
cellmap_flow/norm/models.py
cellmap_flow/post/__init__.py
cellmap_flow/post/postprocessors.py
cellmap_flow/utils/__init__.py
cellmap_flow/utils/bsub_utils.py
cellmap_flow/utils/config_utils.py
cellmap_flow/utils/data.py
cellmap_flow/utils/ds.py
cellmap_flow/utils/load_py.py
cellmap_flow/utils/neuroglancer_utils.py
cellmap_flow/utils/scale_pyramid.py
cellmap_flow/utils/web_utils.py
cellmap_flow-0.1.4.dist-info/licenses/LICENSE
example/cellpose_model.py
example/check_norm.py
example/dacapo_run.py
example/dacapo_run_retrieve.py
example/generate_slider.py
example/larissa_lsd.py
example/model_setup04.py
example/model_setup04_dacapo.py
example/model_spec.py
example/model_spec_run07.py
example/model_spec_run07_7hk.py
example/omnx_model.py
example/omnx_model_converted.py
example/server_check.py
example/tensorflow_acrlsd.py
example/tensorflow_lsd.py
tests/__init__.py
tests/script_test/__init__.py
tests/script_test/fake_model_script.py
cellmap_flow-0.1.4.dist-info/METADATA
cellmap_flow-0.1.4.dist-info/WHEEL
cellmap_flow-0.1.4.dist-info/entry_points.txt
cellmap_flow-0.1.4.dist-info/top_level.txt
cellmap_flow-0.1.4.dist-info/RECORD
