Metadata-Version: 2.4
Name: cellmap-flow
Version: 0.1.4
Summary: Realtime prediction using neuroglancer
Author-email: David Ackerman <ackermand@hhmi.org>, Marwan Zouinkhi <zouinkhim@hhmi.org>
License: BSD 3-Clause License
Requires-Python: <4.0,>=3.11
License-File: LICENSE
Requires-Dist: pymorton
Requires-Dist: numpy
Requires-Dist: PyYAML
Requires-Dist: gunicorn
Requires-Dist: fastremap
Requires-Dist: fastmorph
Requires-Dist: flask
Requires-Dist: flask-cors
Requires-Dist: tensorstore
Requires-Dist: funlib.geometry
Requires-Dist: marshmallow
Requires-Dist: scikit-image
Requires-Dist: flasgger
Requires-Dist: numcodecs
Requires-Dist: zarr==2.18.4
Requires-Dist: h5py
Requires-Dist: s3fs
Requires-Dist: torch
Requires-Dist: universal_pathlib
Requires-Dist: mwatershed
Requires-Dist: funlib.math
Requires-Dist: neuroglancer
Requires-Dist: pydantic
Provides-Extra: dacapo
Requires-Dist: dacapo-ml; extra == "dacapo"
Provides-Extra: cellpose
Requires-Dist: cellpose==3.1.1.1; extra == "cellpose"
Provides-Extra: bioimageio
Requires-Dist: bioimageio.core[onnx,pytorch]==0.7.0; extra == "bioimageio"
Provides-Extra: test
Requires-Dist: pytest; extra == "test"
Requires-Dist: pytest-cov; extra == "test"
Requires-Dist: pytest-lazy-fixtures; extra == "test"
Provides-Extra: dev
Requires-Dist: black; extra == "dev"
Requires-Dist: mypy; extra == "dev"
Requires-Dist: pdbpp; extra == "dev"
Requires-Dist: rich; extra == "dev"
Requires-Dist: ruff; extra == "dev"
Requires-Dist: pre-commit; extra == "dev"
Provides-Extra: docs
Requires-Dist: sphinx-autodoc-typehints; extra == "docs"
Requires-Dist: sphinx-autoapi; extra == "docs"
Requires-Dist: sphinx-click; extra == "docs"
Requires-Dist: sphinx-rtd-theme; extra == "docs"
Requires-Dist: myst-parser; extra == "docs"
Dynamic: license-file
